{
  "activities": {
    "worship-services": {
      "title_i18n": "activitiesDetail.worship.title",
      "subtitle_i18n": "activities.worship.desc",
      "background_image": "images/church.jpg",
      "page_key": "worship",
      "related_links": [
        {
          "url": "youth-programs.html",
          "text": "Youth Programs"
        },
        {
          "url": "family-activities.html",
          "text": "Family Activities"
        },
        {
          "url": "language-classes.html",
          "text": "Language Classes"
        }
      ]
    },
    "youth-programs": {
      "title_i18n": "activitiesDetail.youth.title",
      "subtitle_i18n": "activities.youth.desc",
      "background_image": "images/youth.avif",
      "page_key": "youth",
      "related_links": [
        {
          "url": "worship-services.html",
          "text": "Church Services"
        },
        {
          "url": "family-activities.html",
          "text": "Family Activities"
        },
        {
          "url": "young-adult-activities.html",
          "text": "Young Adult Activities"
        }
      ]
    },
    "family-activities": {
      "title_i18n": "activitiesDetail.family.title",
      "subtitle_i18n": "activities.family.desc",
      "background_image": "images/family.jpg",
      "page_key": "family",
      "related_links": [
        {
          "url": "worship-services.html",
          "text": "Church Services"
        },
        {
          "url": "youth-programs.html",
          "text": "Youth Programs"
        },
        {
          "url": "other-opportunities.html",
          "text": "Other Opportunities"
        }
      ]
    },
    "young-adult-activities": {
      "title_i18n": "activitiesDetail.education.title",
      "subtitle_i18n": "activities.education.desc",
      "background_image": "images/young-adult.avif",
      "page_key": "education",
      "related_links": [
        {
          "url": "youth-programs.html",
          "text": "Youth Programs"
        },
        {
          "url": "language-classes.html",
          "text": "Language Classes"
        },
        {
          "url": "other-opportunities.html",
          "text": "Other Opportunities"
        }
      ]
    },
    "language-classes": {
      "title_i18n": "activitiesDetail.service.title",
      "subtitle_i18n": "activities.service.desc",
      "background_image": "images/language.avif",
      "page_key": "service",
      "related_links": [
        {
          "url": "worship-services.html",
          "text": "Church Services"
        },
        {
          "url": "young-adult-activities.html",
          "text": "Young Adult Activities"
        },
        {
          "url": "other-opportunities.html",
          "text": "Other Opportunities"
        }
      ]
    },
    "other-opportunities": {
      "title_i18n": "activitiesDetail.other.title",
      "subtitle_i18n": "activities.other.desc",
      "background_image": "images/other-activities.jpeg",
      "page_key": "other",
      "related_links": [
        {
          "url": "worship-services.html",
          "text": "Church Services"
        },
        {
          "url": "family-activities.html",
          "text": "Family Activities"
        },
        {
          "url": "language-classes.html",
          "text": "Language Classes"
        }
      ]
    }
  },
  "doctrine": {
    "baptism": {
      "title_i18n": "doctrinePages.baptism.title",
      "subtitle_i18n": "doctrinePages.baptism.subtitle",
      "background_image": "images/bautismo.jpeg",
      "page_key": "baptism",
      "related_links": [
        {
          "url": "jesus-christ.html",
          "text": "Jesus Christ"
        },
        {
          "url": "book-of-mormon.html",
          "text": "Book of Mormon"
        },
        {
          "url": "eternal-families.html",
          "text": "Eternal Families"
        },
        {
          "url": "plan-of-salvation.html",
          "text": "Plan of Salvation"
        }
      ]
    },
    "jesus-christ": {
      "title_i18n": "doctrinePages.jesusChrist.title",
      "subtitle_i18n": "doctrinePages.jesusChrist.subtitle",
      "background_image": "images/jesus.webp",
      "page_key": "jesus-christ",
      "related_links": [
        {
          "url": "plan-of-salvation.html",
          "text": "Plan of Salvation"
        },
        {
          "url": "book-of-mormon.html",
          "text": "Book of Mormon"
        },
        {
          "url": "eternal-families.html",
          "text": "Eternal Families"
        }
      ]
    },
    "book-of-mormon": {
      "title_i18n": "doctrinePages.bookOfMormon.title",
      "subtitle_i18n": "doctrinePages.bookOfMormon.subtitle",
      "background_image": "images/bookofmormonnew.jpg",
      "page_key": "book-of-mormon",
      "related_links": [
        {
          "url": "jesus-christ.html",
          "text": "Jesus Christ"
        },
        {
          "url": "living-prophets.html",
          "text": "Living Prophets"
        },
        {
          "url": "plan-of-salvation.html",
          "text": "Plan of Salvation"
        }
      ]
    },
    "eternal-families": {
      "title_i18n": "doctrinePages.eternalFamilies.title",
      "subtitle_i18n": "doctrinePages.eternalFamilies.subtitle",
      "background_image": "images/family.jpg",
      "page_key": "eternal-families",
      "related_links": [
        {
          "url": "jesus-christ.html",
          "text": "Jesus Christ"
        },
        {
          "url": "plan-of-salvation.html",
          "text": "Plan of Salvation"
        },
        {
          "url": "book-of-mormon.html",
          "text": "Book of Mormon"
        }
      ]
    },
    "living-prophets": {
      "title_i18n": "doctrinePages.livingProphets.title",
      "subtitle_i18n": "doctrinePages.livingProphets.subtitle",
      "background_image": "images/prophet.jpeg",
      "page_key": "living-prophets",
      "related_links": [
        {
          "url": "jesus-christ.html",
          "text": "Jesus Christ"
        },
        {
          "url": "book-of-mormon.html",
          "text": "Book of Mormon"
        },
        {
          "url": "plan-of-salvation.html",
          "text": "Plan of Salvation"
        }
      ]
    },
    "plan-of-salvation": {
      "title_i18n": "doctrinePages.planOfSalvation.title",
      "subtitle_i18n": "doctrinePages.planOfSalvation.subtitle",
      "background_image": "images/salvation.jpg",
      "page_key": "plan-of-salvation",
      "related_links": [
        {
          "url": "jesus-christ.html",
          "text": "Jesus Christ"
        },
        {
          "url": "eternal-families.html",
          "text": "Eternal Families"
        },
        {
          "url": "book-of-mormon.html",
          "text": "Book of Mormon"
        }
      ]
    }
  }
}